mkdocs_modify_base_url/__init__.py
mkdocs_modify_base_url/plugin.py
mkdocs_modify_base_url-0.0.2.dist-info/LICENSE
mkdocs_modify_base_url-0.0.2.dist-info/METADATA
mkdocs_modify_base_url-0.0.2.dist-info/WHEEL
mkdocs_modify_base_url-0.0.2.dist-info/entry_points.txt
mkdocs_modify_base_url-0.0.2.dist-info/top_level.txt
mkdocs_modify_base_url-0.0.2.dist-info/RECORD
