Metadata-Version: 2.1
Name: mkdocs-modify-base-url
Version: 0.0.2
Summary: mkdocs plugin to control the base_url, for use with mike (for multiple versions) and i18n.
Author-email: Andy Goldstein <andy.goldstein@gmail.com>
Project-URL: Homepage, https://github.com/ncdc/mkdocs-modify-base-url
Project-URL: Bug Tracker, https://github.com/ncdc/mkdocs-modify-base-url/issues
Classifier: Programming Language :: Python :: 3
Classifier: License :: OSI Approved :: Apache Software License
Classifier: Operating System :: OS Independent
Requires-Python: >=3.7
License-File: LICENSE
Requires-Dist: mkdocs (>=1)
